castlabs_evs/__init__.py
castlabs_evs/account.py
castlabs_evs/auth.py
castlabs_evs/vmp.py
castlabs_evs/cli/__init__.py
castlabs_evs/cli/account.py
castlabs_evs/cli/vmp.py
castlabs_evs/core/__init__.py
castlabs_evs/core/error.py
castlabs_evs/core/failure.py
castlabs_evs/core/util.py
castlabs_evs-1.1.5.dist-info/METADATA
castlabs_evs-1.1.5.dist-info/WHEEL
castlabs_evs-1.1.5.dist-info/entry_points.txt
castlabs_evs-1.1.5.dist-info/top_level.txt
castlabs_evs-1.1.5.dist-info/RECORD
