Metadata-Version: 2.1
Name: castlabs-evs
Version: 1.1.5
Summary: A client for EVS, Widevine/VMP signing service
Home-page: https://github.com/castlabs/electron-releases/wiki/EVS
Author: Emil Pettersson
Author-email: emil.pettersson@castlabs.com
License: APACHE 2.0
Keywords: castlabs evs 3pl widevine vmp drm electron wvvmp ecs
Classifier: Development Status :: 5 - Production/Stable
Classifier: Environment :: Console
Classifier: Intended Audience :: Developers
Classifier: License :: OSI Approved :: Apache Software License
Classifier: Operating System :: OS Independent
Classifier: Programming Language :: Python :: 3 :: Only
Classifier: Programming Language :: Python :: 3.7
Classifier: Programming Language :: Python :: 3.8
Classifier: Programming Language :: Python :: 3.9
Classifier: Programming Language :: Python :: 3.10
Classifier: Programming Language :: Python :: 3.11
Classifier: Programming Language :: Python :: 3.12
Classifier: Topic :: Software Development :: Build Tools
Classifier: Topic :: Utilities
Requires-Python: >=3.7
Requires-Dist: boto3
Requires-Dist: cryptography
Requires-Dist: macholib
Requires-Dist: requests
